pxpaypy/__init__.py
pxpaypy/helper.py
pxpaypy/pxpay.py
pxpaypy/pxpost.py
PxPayPy-0.1.3a1.dist-info/LICENSE
PxPayPy-0.1.3a1.dist-info/METADATA
PxPayPy-0.1.3a1.dist-info/WHEEL
PxPayPy-0.1.3a1.dist-info/top_level.txt
PxPayPy-0.1.3a1.dist-info/RECORD
