Metadata-Version: 2.1
Name: PxPayPy
Version: 0.1.3a1
Summary: Python library for DPS PaymentExpress PxPay 2.0 API.
Home-page: https://github.com/InternetNZ/pxpaypy
Author: Kesara Rathnayake
Author-email: kesara@internetnz.net.nz
License: GNU AGPL v3
Keywords: dps paymentexpress pxpay pxpost api
Platform: UNKNOWN
Requires-Dist: defusedxml (>=0.5)
Requires-Dist: requests (>=2.20)
